venturi/__init__.py
venturi/_util.py
venturi/config.py
venturi/core.py
venturi/base_config.yaml
venturi-0.9.2.dist-info/METADATA
venturi-0.9.2.dist-info/WHEEL
venturi-0.9.2.dist-info/entry_points.txt
venturi-0.9.2.dist-info/licenses/LICENSE
venturi-0.9.2.dist-info/RECORD
